ChangeLog.rst
LICENSE
MANIFEST.in
README.rst
setup.cfg
setup.py
jqp/__init__.py
jqp.egg-info/PKG-INFO
jqp.egg-info/SOURCES.txt
jqp.egg-info/dependency_links.txt
jqp.egg-info/top_level.txt
scripts/jqp
tests/__init__.py
tests/run_test.py