Metadata-Version: 1.1
Name: jqp
Version: 0.1.0
Summary: JSON processor with Python one-liner
Home-page: https://github.com/unnonouno/jqp
Author: Yuya Unno
Author-email: unnonouno@gmail.com
License: MIT License
Platform: UNKNOWN
Classifier: Operating System :: OS Independent
Classifier: Environment :: Console
Classifier: Programming Language :: Python
Classifier: License :: OSI Approved :: MIT License
Classifier: Development Status :: 2 - Pre-Alpha
Classifier: Intended Audience :: Information Technology
Classifier: Topic :: Utilities
